mailmq
