Metadata-Version: 1.1
Name: mailmq
Version: 0.0.4
Summary: Sendmail compatible SMTP relay over MQ
Home-page: https://github.com/squareweave/mailmq
Author: Danielle Madeley
Author-email: danielle.madeley@squareweave.com.au
License: UNKNOWN
Platform: UNKNOWN
Classifier: License :: OSI Approved :: MIT License
Classifier: Programming Language :: Python
Classifier: Programming Language :: Python :: 3
